{
  "item": [
    {
      "id": "a8e4bf9e-c8b3-4fbd-84a6-5fcd0c07ceeb",
      "name": "Sketch",
      "description": {
        "content": "Generate images from hand-drawn sketches or line drawings, guided by a text prompt to fill in details, colors, and textures.",
        "type": "text/plain"
      },
      "item": [
        {
          "id": "eedd6979-ae10-49c4-a643-f9ccb9394036",
          "name": "Generate an image from a sketch",
          "request": {
            "name": "Generate an image from a sketch",
            "description": {
              "content": "Generates a detailed image from a hand-drawn sketch or line drawing. The sketch provides the structural composition while the text prompt guides the content, colors, textures, and style of the output image.",
              "type": "text/plain"
            },
            "url": {
              "path": [
                "v2beta",
                "stable-image",
                "control",
                "sketch"
              ],
              "host": [
                "{{baseUrl}}"
              ],
              "query": [],
              "variable": []
            },
            "header": [
              {
                "key": "Content-Type",
                "value": "multipart/form-data"
              },
              {
                "key": "Accept",
                "value": "image/jpeg"
              }
            ],
            "method": "POST",
            "auth": null,
            "body": {
              "mode": "formdata",
              "formdata": [
                {
                  "key": "image",
                  "type": "file",
                  "description": "(Required) The sketch or line drawing image to use as structural guidance."
                },
                {
                  "key": "prompt",
                  "value": "<string>",
                  "type": "text",
                  "description": "(Required) Text describing the desired output image including content, colors, textures, and style."
                },
                {
                  "key": "negative_prompt",
                  "value": "<string>",
                  "type": "text",
                  "description": "Text describing elements to exclude from the output image."
                },
                {
                  "key": "control_strength",
                  "value": "0.7",
                  "type": "text",
                  "description": "Controls how closely the output follows the input sketch. Higher values produce outputs more faithful to the sketch structure."
                },
                {
                  "key": "seed",
                  "value": "0",
                  "type": "text",
                  "description": "A value to control randomness in generation."
                },
                {
                  "key": "output_format",
                  "value": "png",
                  "type": "text",
                  "description": "The output format of the generated image. (This can only be one of jpeg,png,webp)"
                }
              ]
            }
          },
          "response": [
            {
              "id": "c29dfbf7-e220-4ad2-a334-948d982f167d",
              "name": "Successfully generated image from sketch",
              "originalRequest": {
                "url": {
                  "path": [
                    "v2beta",
                    "stable-image",
                    "control",
                    "sketch"
                  ],
                  "host": [
                    "{{baseUrl}}"
                  ],
                  "query": [],
                  "variable": []
                },
                "header": [
                  {
                    "description": {
                      "content": "Added as a part of security scheme: bearer",
                      "type": "text/plain"
                    },
                    "key": "Authorization",
                    "value": "Bearer <token>"
                  },
                  {
                    "key": "Accept",
                    "value": "image/jpeg"
                  }
                ],
                "method": "POST",
                "body": {
                  "mode": "formdata",
                  "formdata": [
                    {
                      "description": {
                        "content": "(Required) The sketch or line drawing image to use as structural guidance.",
                        "type": "text/plain"
                      },
                      "key": "image",
                      "value": "<binary>",
                      "type": "text"
                    },
                    {
                      "description": {
                        "content": "(Required) Text describing the desired output image including content, colors, textures, and style.",
                        "type": "text/plain"
                      },
                      "key": "prompt",
                      "value": "<string>",
                      "type": "text"
                    },
                    {
                      "description": {
                        "content": "Text describing elements to exclude from the output image.",
                        "type": "text/plain"
                      },
                      "key": "negative_prompt",
                      "value": "<string>",
                      "type": "text"
                    },
                    {
                      "description": {
                        "content": "Controls how closely the output follows the input sketch. Higher values produce outputs more faithful to the sketch structure.",
                        "type": "text/plain"
                      },
                      "key": "control_strength",
                      "value": "0.7",
                      "type": "text"
                    },
                    {
                      "description": {
                        "content": "A value to control randomness in generation.",
                        "type": "text/plain"
                      },
                      "key": "seed",
                      "value": "0",
                      "type": "text"
                    },
                    {
                      "description": {
                        "content": "The output format of the generated image. (This can only be one of jpeg,png,webp)",
                        "type": "text/plain"
                      },
                      "key": "output_format",
                      "value": "png",
                      "type": "text"
                    }
                  ]
                }
              },
              "status": "OK",
              "code": 200,
              "header": [
                {
                  "key": "Content-Type",
                  "value": "application/json"
                }
              ],
              "body": "{\n  \"image\": \"string\",\n  \"finish_reason\": \"SUCCESS\",\n  \"seed\": 4216\n}",
              "cookie": [],
              "_postman_previewlanguage": "json"
            },
            {
              "id": "a846caf6-8912-4db2-8ecd-c9c5715a234a",
              "name": "Bad request due to invalid parameters",
              "originalRequest": {
                "url": {
                  "path": [
                    "v2beta",
                    "stable-image",
                    "control",
                    "sketch"
                  ],
                  "host": [
                    "{{baseUrl}}"
                  ],
                  "query": [],
                  "variable": []
                },
                "header": [
                  {
                    "description": {
                      "content": "Added as a part of security scheme: bearer",
                      "type": "text/plain"
                    },
                    "key": "Authorization",
                    "value": "Bearer <token>"
                  },
                  {
                    "key": "Accept",
                    "value": "application/json"
                  }
                ],
                "method": "POST",
                "body": {
                  "mode": "formdata",
                  "formdata": [
                    {
                      "description": {
                        "content": "(Required) The sketch or line drawing image to use as structural guidance.",
                        "type": "text/plain"
                      },
                      "key": "image",
                      "value": "<binary>",
                      "type": "text"
                    },
                    {
                      "description": {
                        "content": "(Required) Text describing the desired output image including content, colors, textures, and style.",
                        "type": "text/plain"
                      },
                      "key": "prompt",
                      "value": "<string>",
                      "type": "text"
                    },
                    {
                      "description": {
                        "content": "Text describing elements to exclude from the output image.",
                        "type": "text/plain"
                      },
                      "key": "negative_prompt",
                      "value": "<string>",
                      "type": "text"
                    },
                    {
                      "description": {
                        "content": "Controls how closely the output follows the input sketch. Higher values produce outputs more faithful to the sketch structure.",
                        "type": "text/plain"
                      },
                      "key": "control_strength",
                      "value": "0.7",
                      "type": "text"
                    },
                    {
                      "description": {
                        "content": "A value to control randomness in generation.",
                        "type": "text/plain"
                      },
                      "key": "seed",
                      "value": "0",
                      "type": "text"
                    },
                    {
                      "description": {
                        "content": "The output format of the generated image. (This can only be one of jpeg,png,webp)",
                        "type": "text/plain"
                      },
                      "key": "output_format",
                      "value": "png",
                      "type": "text"
                    }
                  ]
                }
              },
              "status": "Bad Request",
              "code": 400,
              "header": [
                {
                  "key": "Content-Type",
                  "value": "application/json"
                }
              ],
              "body": "{\n  \"id\": \"string\",\n  \"name\": \"string\",\n  \"message\": \"string\"\n}",
              "cookie": [],
              "_postman_previewlanguage": "json"
            },
            {
              "id": "a6b0135f-9b43-4e12-aca7-67bbe5b81e8e",
              "name": "Unauthorized due to missing or invalid API key",
              "originalRequest": {
                "url": {
                  "path": [
                    "v2beta",
                    "stable-image",
                    "control",
                    "sketch"
                  ],
                  "host": [
                    "{{baseUrl}}"
                  ],
                  "query": [],
                  "variable": []
                },
                "header": [
                  {
                    "description": {
                      "content": "Added as a part of security scheme: bearer",
                      "type": "text/plain"
                    },
                    "key": "Authorization",
                    "value": "Bearer <token>"
                  },
                  {
                    "key": "Accept",
                    "value": "application/json"
                  }
                ],
                "method": "POST",
                "body": {
                  "mode": "formdata",
                  "formdata": [
                    {
                      "description": {
                        "content": "(Required) The sketch or line drawing image to use as structural guidance.",
                        "type": "text/plain"
                      },
                      "key": "image",
                      "value": "<binary>",
                      "type": "text"
                    },
                    {
                      "description": {
                        "content": "(Required) Text describing the desired output image including content, colors, textures, and style.",
                        "type": "text/plain"
                      },
                      "key": "prompt",
                      "value": "<string>",
                      "type": "text"
                    },
                    {
                      "description": {
                        "content": "Text describing elements to exclude from the output image.",
                        "type": "text/plain"
                      },
                      "key": "negative_prompt",
                      "value": "<string>",
                      "type": "text"
                    },
                    {
                      "description": {
                        "content": "Controls how closely the output follows the input sketch. Higher values produce outputs more faithful to the sketch structure.",
                        "type": "text/plain"
                      },
                      "key": "control_strength",
                      "value": "0.7",
                      "type": "text"
                    },
                    {
                      "description": {
                        "content": "A value to control randomness in generation.",
                        "type": "text/plain"
                      },
                      "key": "seed",
                      "value": "0",
                      "type": "text"
                    },
                    {
                      "description": {
                        "content": "The output format of the generated image. (This can only be one of jpeg,png,webp)",
                        "type": "text/plain"
                      },
                      "key": "output_format",
                      "value": "png",
                      "type": "text"
                    }
                  ]
                }
              },
              "status": "Unauthorized",
              "code": 401,
              "header": [
                {
                  "key": "Content-Type",
                  "value": "application/json"
                }
              ],
              "body": "{\n  \"id\": \"string\",\n  \"name\": \"string\",\n  \"message\": \"string\"\n}",
              "cookie": [],
              "_postman_previewlanguage": "json"
            },
            {
              "id": "f36956fd-46de-4f2b-92d1-2082a66e592e",
              "name": "Forbidden due to content moderation or insufficient permissions",
              "originalRequest": {
                "url": {
                  "path": [
                    "v2beta",
                    "stable-image",
                    "control",
                    "sketch"
                  ],
                  "host": [
                    "{{baseUrl}}"
                  ],
                  "query": [],
                  "variable": []
                },
                "header": [
                  {
                    "description": {
                      "content": "Added as a part of security scheme: bearer",
                      "type": "text/plain"
                    },
                    "key": "Authorization",
                    "value": "Bearer <token>"
                  },
                  {
                    "key": "Accept",
                    "value": "application/json"
                  }
                ],
                "method": "POST",
                "body": {
                  "mode": "formdata",
                  "formdata": [
                    {
                      "description": {
                        "content": "(Required) The sketch or line drawing image to use as structural guidance.",
                        "type": "text/plain"
                      },
                      "key": "image",
                      "value": "<binary>",
                      "type": "text"
                    },
                    {
                      "description": {
                        "content": "(Required) Text describing the desired output image including content, colors, textures, and style.",
                        "type": "text/plain"
                      },
                      "key": "prompt",
                      "value": "<string>",
                      "type": "text"
                    },
                    {
                      "description": {
                        "content": "Text describing elements to exclude from the output image.",
                        "type": "text/plain"
                      },
                      "key": "negative_prompt",
                      "value": "<string>",
                      "type": "text"
                    },
                    {
                      "description": {
                        "content": "Controls how closely the output follows the input sketch. Higher values produce outputs more faithful to the sketch structure.",
                        "type": "text/plain"
                      },
                      "key": "control_strength",
                      "value": "0.7",
                      "type": "text"
                    },
                    {
                      "description": {
                        "content": "A value to control randomness in generation.",
                        "type": "text/plain"
                      },
                      "key": "seed",
                      "value": "0",
                      "type": "text"
                    },
                    {
                      "description": {
                        "content": "The output format of the generated image. (This can only be one of jpeg,png,webp)",
                        "type": "text/plain"
                      },
                      "key": "output_format",
                      "value": "png",
                      "type": "text"
                    }
                  ]
                }
              },
              "status": "Forbidden",
              "code": 403,
              "header": [
                {
                  "key": "Content-Type",
                  "value": "application/json"
                }
              ],
              "body": "{\n  \"id\": \"string\",\n  \"name\": \"string\",\n  \"message\": \"string\"\n}",
              "cookie": [],
              "_postman_previewlanguage": "json"
            },
            {
              "id": "9af85272-1a8f-45b8-b2aa-4163758428d6",
              "name": "Rate limit exceeded",
              "originalRequest": {
                "url": {
                  "path": [
                    "v2beta",
                    "stable-image",
                    "control",
                    "sketch"
                  ],
                  "host": [
                    "{{baseUrl}}"
                  ],
                  "query": [],
                  "variable": []
                },
                "header": [
                  {
                    "description": {
                      "content": "Added as a part of security scheme: bearer",
                      "type": "text/plain"
                    },
                    "key": "Authorization",
                    "value": "Bearer <token>"
                  },
                  {
                    "key": "Accept",
                    "value": "application/json"
                  }
                ],
                "method": "POST",
                "body": {
                  "mode": "formdata",
                  "formdata": [
                    {
                      "description": {
                        "content": "(Required) The sketch or line drawing image to use as structural guidance.",
                        "type": "text/plain"
                      },
                      "key": "image",
                      "value": "<binary>",
                      "type": "text"
                    },
                    {
                      "description": {
                        "content": "(Required) Text describing the desired output image including content, colors, textures, and style.",
                        "type": "text/plain"
                      },
                      "key": "prompt",
                      "value": "<string>",
                      "type": "text"
                    },
                    {
                      "description": {
                        "content": "Text describing elements to exclude from the output image.",
                        "type": "text/plain"
                      },
                      "key": "negative_prompt",
                      "value": "<string>",
                      "type": "text"
                    },
                    {
                      "description": {
                        "content": "Controls how closely the output follows the input sketch. Higher values produce outputs more faithful to the sketch structure.",
                        "type": "text/plain"
                      },
                      "key": "control_strength",
                      "value": "0.7",
                      "type": "text"
                    },
                    {
                      "description": {
                        "content": "A value to control randomness in generation.",
                        "type": "text/plain"
                      },
                      "key": "seed",
                      "value": "0",
                      "type": "text"
                    },
                    {
                      "description": {
                        "content": "The output format of the generated image. (This can only be one of jpeg,png,webp)",
                        "type": "text/plain"
                      },
                      "key": "output_format",
                      "value": "png",
                      "type": "text"
                    }
                  ]
                }
              },
              "status": "Too Many Requests",
              "code": 429,
              "header": [
                {
                  "key": "Content-Type",
                  "value": "application/json"
                }
              ],
              "body": "{\n  \"id\": \"string\",\n  \"name\": \"string\",\n  \"message\": \"string\"\n}",
              "cookie": [],
              "_postman_previewlanguage": "json"
            }
          ],
          "event": [],
          "protocolProfileBehavior": {
            "disableBodyPruning": true
          }
        }
      ],
      "event": []
    },
    {
      "id": "72ce796a-c679-411d-8a02-b112ef478268",
      "name": "Structure",
      "description": {
        "content": "Generate images guided by the structural composition of a reference image, preserving edges and layout while applying new content from a text prompt.",
        "type": "text/plain"
      },
      "item": [
        {
          "id": "c364cd84-e353-4072-9908-233015e05857",
          "name": "Generate an image guided by structural reference",
          "request": {
            "name": "Generate an image guided by structural reference",
            "description": {
              "content": "Generates a new image guided by the structural composition of a reference image. The reference image provides edge and layout information while the text prompt directs the content and style of the output. Useful for generating variations that maintain the same composition.",
              "type": "text/plain"
            },
            "url": {
              "path": [
                "v2beta",
                "stable-image",
                "control",
                "structure"
              ],
              "host": [
                "{{baseUrl}}"
              ],
              "query": [],
              "variable": []
            },
            "header": [
              {
                "key": "Content-Type",
                "value": "multipart/form-data"
              },
              {
                "key": "Accept",
                "value": "image/jpeg"
              }
            ],
            "method": "POST",
            "auth": null,
            "body": {
              "mode": "formdata",
              "formdata": [
                {
                  "key": "image",
                  "type": "file",
                  "description": "(Required) The reference image to use for structural guidance. The edges and layout of this image will guide the output composition."
                },
                {
                  "key": "prompt",
                  "value": "<string>",
                  "type": "text",
                  "description": "(Required) Text describing the desired output image content and style."
                },
                {
                  "key": "negative_prompt",
                  "value": "<string>",
                  "type": "text",
                  "description": "Text describing elements to exclude from the output image."
                },
                {
                  "key": "control_strength",
                  "value": "0.7",
                  "type": "text",
                  "description": "Controls how closely the output follows the reference structure. Higher values produce outputs more faithful to the reference layout."
                },
                {
                  "key": "seed",
                  "value": "0",
                  "type": "text",
                  "description": "A value to control randomness in generation."
                },
                {
                  "key": "output_format",
                  "value": "png",
                  "type": "text",
                  "description": "The output format of the generated image. (This can only be one of jpeg,png,webp)"
                }
              ]
            }
          },
          "response": [
            {
              "id": "177d3831-8ba2-4992-ab38-87ed8dc8057d",
              "name": "Successfully generated structurally guided image",
              "originalRequest": {
                "url": {
                  "path": [
                    "v2beta",
                    "stable-image",
                    "control",
                    "structure"
                  ],
                  "host": [
                    "{{baseUrl}}"
                  ],
                  "query": [],
                  "variable": []
                },
                "header": [
                  {
                    "description": {
                      "content": "Added as a part of security scheme: bearer",
                      "type": "text/plain"
                    },
                    "key": "Authorization",
                    "value": "Bearer <token>"
                  },
                  {
                    "key": "Accept",
                    "value": "image/jpeg"
                  }
                ],
                "method": "POST",
                "body": {
                  "mode": "formdata",
                  "formdata": [
                    {
                      "description": {
                        "content": "(Required) The reference image to use for structural guidance. The edges and layout of this image will guide the output composition.",
                        "type": "text/plain"
                      },
                      "key": "image",
                      "value": "<binary>",
                      "type": "text"
                    },
                    {
                      "description": {
                        "content": "(Required) Text describing the desired output image content and style.",
                        "type": "text/plain"
                      },
                      "key": "prompt",
                      "value": "<string>",
                      "type": "text"
                    },
                    {
                      "description": {
                        "content": "Text describing elements to exclude from the output image.",
                        "type": "text/plain"
                      },
                      "key": "negative_prompt",
                      "value": "<string>",
                      "type": "text"
                    },
                    {
                      "description": {
                        "content": "Controls how closely the output follows the reference structure. Higher values produce outputs more faithful to the reference layout.",
                        "type": "text/plain"
                      },
                      "key": "control_strength",
                      "value": "0.7",
                      "type": "text"
                    },
                    {
                      "description": {
                        "content": "A value to control randomness in generation.",
                        "type": "text/plain"
                      },
                      "key": "seed",
                      "value": "0",
                      "type": "text"
                    },
                    {
                      "description": {
                        "content": "The output format of the generated image. (This can only be one of jpeg,png,webp)",
                        "type": "text/plain"
                      },
                      "key": "output_format",
                      "value": "png",
                      "type": "text"
                    }
                  ]
                }
              },
              "status": "OK",
              "code": 200,
              "header": [
                {
                  "key": "Content-Type",
                  "value": "application/json"
                }
              ],
              "body": "{\n  \"image\": \"string\",\n  \"finish_reason\": \"SUCCESS\",\n  \"seed\": 4216\n}",
              "cookie": [],
              "_postman_previewlanguage": "json"
            },
            {
              "id": "32999e7f-223e-48aa-be15-4c89498baead",
              "name": "Bad request due to invalid parameters",
              "originalRequest": {
                "url": {
                  "path": [
                    "v2beta",
                    "stable-image",
                    "control",
                    "structure"
                  ],
                  "host": [
                    "{{baseUrl}}"
                  ],
                  "query": [],
                  "variable": []
                },
                "header": [
                  {
                    "description": {
                      "content": "Added as a part of security scheme: bearer",
                      "type": "text/plain"
                    },
                    "key": "Authorization",
                    "value": "Bearer <token>"
                  },
                  {
                    "key": "Accept",
                    "value": "application/json"
                  }
                ],
                "method": "POST",
                "body": {
                  "mode": "formdata",
                  "formdata": [
                    {
                      "description": {
                        "content": "(Required) The reference image to use for structural guidance. The edges and layout of this image will guide the output composition.",
                        "type": "text/plain"
                      },
                      "key": "image",
                      "value": "<binary>",
                      "type": "text"
                    },
                    {
                      "description": {
                        "content": "(Required) Text describing the desired output image content and style.",
                        "type": "text/plain"
                      },
                      "key": "prompt",
                      "value": "<string>",
                      "type": "text"
                    },
                    {
                      "description": {
                        "content": "Text describing elements to exclude from the output image.",
                        "type": "text/plain"
                      },
                      "key": "negative_prompt",
                      "value": "<string>",
                      "type": "text"
                    },
                    {
                      "description": {
                        "content": "Controls how closely the output follows the reference structure. Higher values produce outputs more faithful to the reference layout.",
                        "type": "text/plain"
                      },
                      "key": "control_strength",
                      "value": "0.7",
                      "type": "text"
                    },
                    {
                      "description": {
                        "content": "A value to control randomness in generation.",
                        "type": "text/plain"
                      },
                      "key": "seed",
                      "value": "0",
                      "type": "text"
                    },
                    {
                      "description": {
                        "content": "The output format of the generated image. (This can only be one of jpeg,png,webp)",
                        "type": "text/plain"
                      },
                      "key": "output_format",
                      "value": "png",
                      "type": "text"
                    }
                  ]
                }
              },
              "status": "Bad Request",
              "code": 400,
              "header": [
                {
                  "key": "Content-Type",
                  "value": "application/json"
                }
              ],
              "body": "{\n  \"id\": \"string\",\n  \"name\": \"string\",\n  \"message\": \"string\"\n}",
              "cookie": [],
              "_postman_previewlanguage": "json"
            },
            {
              "id": "cf44950d-ec3f-4901-b636-404d4c3317d2",
              "name": "Unauthorized due to missing or invalid API key",
              "originalRequest": {
                "url": {
                  "path": [
                    "v2beta",
                    "stable-image",
                    "control",
                    "structure"
                  ],
                  "host": [
                    "{{baseUrl}}"
                  ],
                  "query": [],
                  "variable": []
                },
                "header": [
                  {
                    "description": {
                      "content": "Added as a part of security scheme: bearer",
                      "type": "text/plain"
                    },
                    "key": "Authorization",
                    "value": "Bearer <token>"
                  },
                  {
                    "key": "Accept",
                    "value": "application/json"
                  }
                ],
                "method": "POST",
                "body": {
                  "mode": "formdata",
                  "formdata": [
                    {
                      "description": {
                        "content": "(Required) The reference image to use for structural guidance. The edges and layout of this image will guide the output composition.",
                        "type": "text/plain"
                      },
                      "key": "image",
                      "value": "<binary>",
                      "type": "text"
                    },
                    {
                      "description": {
                        "content": "(Required) Text describing the desired output image content and style.",
                        "type": "text/plain"
                      },
                      "key": "prompt",
                      "value": "<string>",
                      "type": "text"
                    },
                    {
                      "description": {
                        "content": "Text describing elements to exclude from the output image.",
                        "type": "text/plain"
                      },
                      "key": "negative_prompt",
                      "value": "<string>",
                      "type": "text"
                    },
                    {
                      "description": {
                        "content": "Controls how closely the output follows the reference structure. Higher values produce outputs more faithful to the reference layout.",
                        "type": "text/plain"
                      },
                      "key": "control_strength",
                      "value": "0.7",
                      "type": "text"
                    },
                    {
                      "description": {
                        "content": "A value to control randomness in generation.",
                        "type": "text/plain"
                      },
                      "key": "seed",
                      "value": "0",
                      "type": "text"
                    },
                    {
                      "description": {
                        "content": "The output format of the generated image. (This can only be one of jpeg,png,webp)",
                        "type": "text/plain"
                      },
                      "key": "output_format",
                      "value": "png",
                      "type": "text"
                    }
                  ]
                }
              },
              "status": "Unauthorized",
              "code": 401,
              "header": [
                {
                  "key": "Content-Type",
                  "value": "application/json"
                }
              ],
              "body": "{\n  \"id\": \"string\",\n  \"name\": \"string\",\n  \"message\": \"string\"\n}",
              "cookie": [],
              "_postman_previewlanguage": "json"
            },
            {
              "id": "90b52b5e-3440-439b-882c-d85a2f988b5d",
              "name": "Forbidden due to content moderation or insufficient permissions",
              "originalRequest": {
                "url": {
                  "path": [
                    "v2beta",
                    "stable-image",
                    "control",
                    "structure"
                  ],
                  "host": [
                    "{{baseUrl}}"
                  ],
                  "query": [],
                  "variable": []
                },
                "header": [
                  {
                    "description": {
                      "content": "Added as a part of security scheme: bearer",
                      "type": "text/plain"
                    },
                    "key": "Authorization",
                    "value": "Bearer <token>"
                  },
                  {
                    "key": "Accept",
                    "value": "application/json"
                  }
                ],
                "method": "POST",
                "body": {
                  "mode": "formdata",
                  "formdata": [
                    {
                      "description": {
                        "content": "(Required) The reference image to use for structural guidance. The edges and layout of this image will guide the output composition.",
                        "type": "text/plain"
                      },
                      "key": "image",
                      "value": "<binary>",
                      "type": "text"
                    },
                    {
                      "description": {
                        "content": "(Required) Text describing the desired output image content and style.",
                        "type": "text/plain"
                      },
                      "key": "prompt",
                      "value": "<string>",
                      "type": "text"
                    },
                    {
                      "description": {
                        "content": "Text describing elements to exclude from the output image.",
                        "type": "text/plain"
                      },
                      "key": "negative_prompt",
                      "value": "<string>",
                      "type": "text"
                    },
                    {
                      "description": {
                        "content": "Controls how closely the output follows the reference structure. Higher values produce outputs more faithful to the reference layout.",
                        "type": "text/plain"
                      },
                      "key": "control_strength",
                      "value": "0.7",
                      "type": "text"
                    },
                    {
                      "description": {
                        "content": "A value to control randomness in generation.",
                        "type": "text/plain"
                      },
                      "key": "seed",
                      "value": "0",
                      "type": "text"
                    },
                    {
                      "description": {
                        "content": "The output format of the generated image. (This can only be one of jpeg,png,webp)",
                        "type": "text/plain"
                      },
                      "key": "output_format",
                      "value": "png",
                      "type": "text"
                    }
                  ]
                }
              },
              "status": "Forbidden",
              "code": 403,
              "header": [
                {
                  "key": "Content-Type",
                  "value": "application/json"
                }
              ],
              "body": "{\n  \"id\": \"string\",\n  \"name\": \"string\",\n  \"message\": \"string\"\n}",
              "cookie": [],
              "_postman_previewlanguage": "json"
            },
            {
              "id": "de60b11f-ffd4-4d57-bd40-5839f4c23228",
              "name": "Rate limit exceeded",
              "originalRequest": {
                "url": {
                  "path": [
                    "v2beta",
                    "stable-image",
                    "control",
                    "structure"
                  ],
                  "host": [
                    "{{baseUrl}}"
                  ],
                  "query": [],
                  "variable": []
                },
                "header": [
                  {
                    "description": {
                      "content": "Added as a part of security scheme: bearer",
                      "type": "text/plain"
                    },
                    "key": "Authorization",
                    "value": "Bearer <token>"
                  },
                  {
                    "key": "Accept",
                    "value": "application/json"
                  }
                ],
                "method": "POST",
                "body": {
                  "mode": "formdata",
                  "formdata": [
                    {
                      "description": {
                        "content": "(Required) The reference image to use for structural guidance. The edges and layout of this image will guide the output composition.",
                        "type": "text/plain"
                      },
                      "key": "image",
                      "value": "<binary>",
                      "type": "text"
                    },
                    {
                      "description": {
                        "content": "(Required) Text describing the desired output image content and style.",
                        "type": "text/plain"
                      },
                      "key": "prompt",
                      "value": "<string>",
                      "type": "text"
                    },
                    {
                      "description": {
                        "content": "Text describing elements to exclude from the output image.",
                        "type": "text/plain"
                      },
                      "key": "negative_prompt",
                      "value": "<string>",
                      "type": "text"
                    },
                    {
                      "description": {
                        "content": "Controls how closely the output follows the reference structure. Higher values produce outputs more faithful to the reference layout.",
                        "type": "text/plain"
                      },
                      "key": "control_strength",
                      "value": "0.7",
                      "type": "text"
                    },
                    {
                      "description": {
                        "content": "A value to control randomness in generation.",
                        "type": "text/plain"
                      },
                      "key": "seed",
                      "value": "0",
                      "type": "text"
                    },
                    {
                      "description": {
                        "content": "The output format of the generated image. (This can only be one of jpeg,png,webp)",
                        "type": "text/plain"
                      },
                      "key": "output_format",
                      "value": "png",
                      "type": "text"
                    }
                  ]
                }
              },
              "status": "Too Many Requests",
              "code": 429,
              "header": [
                {
                  "key": "Content-Type",
                  "value": "application/json"
                }
              ],
              "body": "{\n  \"id\": \"string\",\n  \"name\": \"string\",\n  \"message\": \"string\"\n}",
              "cookie": [],
              "_postman_previewlanguage": "json"
            }
          ],
          "event": [],
          "protocolProfileBehavior": {
            "disableBodyPruning": true
          }
        }
      ],
      "event": []
    },
    {
      "id": "5e6d9972-a388-497e-b323-1df12a8fdb5e",
      "name": "Style",
      "description": {
        "content": "Generate images that adopt the visual style of a reference image while following a text prompt for content direction.",
        "type": "text/plain"
      },
      "item": [
        {
          "id": "d6b50a4f-e40f-40f8-962f-4d346bd2ca4a",
          "name": "Generate an image with style transfer",
          "request": {
            "name": "Generate an image with style transfer",
            "description": {
              "content": "Generates a new image that adopts the visual style of a reference image. The style image provides color palette, artistic technique, and aesthetic direction while the text prompt controls the subject and composition of the output.",
              "type": "text/plain"
            },
            "url": {
              "path": [
                "v2beta",
                "stable-image",
                "control",
                "style"
              ],
              "host": [
                "{{baseUrl}}"
              ],
              "query": [],
              "variable": []
            },
            "header": [
              {
                "key": "Content-Type",
                "value": "multipart/form-data"
              },
              {
                "key": "Accept",
                "value": "image/jpeg"
              }
            ],
            "method": "POST",
            "auth": null,
            "body": {
              "mode": "formdata",
              "formdata": [
                {
                  "key": "image",
                  "type": "file",
                  "description": "(Required) The style reference image whose visual style will be applied to the output."
                },
                {
                  "key": "prompt",
                  "value": "<string>",
                  "type": "text",
                  "description": "(Required) Text describing the subject and composition of the output image."
                },
                {
                  "key": "negative_prompt",
                  "value": "<string>",
                  "type": "text",
                  "description": "Text describing elements to exclude from the output image."
                },
                {
                  "key": "fidelity",
                  "value": "0.5",
                  "type": "text",
                  "description": "Controls how strongly the style of the reference image influences the output. Higher values produce outputs closer to the reference style."
                },
                {
                  "key": "seed",
                  "value": "0",
                  "type": "text",
                  "description": "A value to control randomness in generation."
                },
                {
                  "key": "output_format",
                  "value": "png",
                  "type": "text",
                  "description": "The output format of the generated image. (This can only be one of jpeg,png,webp)"
                }
              ]
            }
          },
          "response": [
            {
              "id": "33a1e53d-aab8-45eb-93dd-ec3917f726d2",
              "name": "Successfully generated style-transferred image",
              "originalRequest": {
                "url": {
                  "path": [
                    "v2beta",
                    "stable-image",
                    "control",
                    "style"
                  ],
                  "host": [
                    "{{baseUrl}}"
                  ],
                  "query": [],
                  "variable": []
                },
                "header": [
                  {
                    "description": {
                      "content": "Added as a part of security scheme: bearer",
                      "type": "text/plain"
                    },
                    "key": "Authorization",
                    "value": "Bearer <token>"
                  },
                  {
                    "key": "Accept",
                    "value": "image/jpeg"
                  }
                ],
                "method": "POST",
                "body": {
                  "mode": "formdata",
                  "formdata": [
                    {
                      "description": {
                        "content": "(Required) The style reference image whose visual style will be applied to the output.",
                        "type": "text/plain"
                      },
                      "key": "image",
                      "value": "<binary>",
                      "type": "text"
                    },
                    {
                      "description": {
                        "content": "(Required) Text describing the subject and composition of the output image.",
                        "type": "text/plain"
                      },
                      "key": "prompt",
                      "value": "<string>",
                      "type": "text"
                    },
                    {
                      "description": {
                        "content": "Text describing elements to exclude from the output image.",
                        "type": "text/plain"
                      },
                      "key": "negative_prompt",
                      "value": "<string>",
                      "type": "text"
                    },
                    {
                      "description": {
                        "content": "Controls how strongly the style of the reference image influences the output. Higher values produce outputs closer to the reference style.",
                        "type": "text/plain"
                      },
                      "key": "fidelity",
                      "value": "0.5",
                      "type": "text"
                    },
                    {
                      "description": {
                        "content": "A value to control randomness in generation.",
                        "type": "text/plain"
                      },
                      "key": "seed",
                      "value": "0",
                      "type": "text"
                    },
                    {
                      "description": {
                        "content": "The output format of the generated image. (This can only be one of jpeg,png,webp)",
                        "type": "text/plain"
                      },
                      "key": "output_format",
                      "value": "png",
                      "type": "text"
                    }
                  ]
                }
              },
              "status": "OK",
              "code": 200,
              "header": [
                {
                  "key": "Content-Type",
                  "value": "application/json"
                }
              ],
              "body": "{\n  \"image\": \"string\",\n  \"finish_reason\": \"SUCCESS\",\n  \"seed\": 4216\n}",
              "cookie": [],
              "_postman_previewlanguage": "json"
            },
            {
              "id": "d37cfc04-bb60-48dd-a77d-4d0e4c217d1c",
              "name": "Bad request due to invalid parameters",
              "originalRequest": {
                "url": {
                  "path": [
                    "v2beta",
                    "stable-image",
                    "control",
                    "style"
                  ],
                  "host": [
                    "{{baseUrl}}"
                  ],
                  "query": [],
                  "variable": []
                },
                "header": [
                  {
                    "description": {
                      "content": "Added as a part of security scheme: bearer",
                      "type": "text/plain"
                    },
                    "key": "Authorization",
                    "value": "Bearer <token>"
                  },
                  {
                    "key": "Accept",
                    "value": "application/json"
                  }
                ],
                "method": "POST",
                "body": {
                  "mode": "formdata",
                  "formdata": [
                    {
                      "description": {
                        "content": "(Required) The style reference image whose visual style will be applied to the output.",
                        "type": "text/plain"
                      },
                      "key": "image",
                      "value": "<binary>",
                      "type": "text"
                    },
                    {
                      "description": {
                        "content": "(Required) Text describing the subject and composition of the output image.",
                        "type": "text/plain"
                      },
                      "key": "prompt",
                      "value": "<string>",
                      "type": "text"
                    },
                    {
                      "description": {
                        "content": "Text describing elements to exclude from the output image.",
                        "type": "text/plain"
                      },
                      "key": "negative_prompt",
                      "value": "<string>",
                      "type": "text"
                    },
                    {
                      "description": {
                        "content": "Controls how strongly the style of the reference image influences the output. Higher values produce outputs closer to the reference style.",
                        "type": "text/plain"
                      },
                      "key": "fidelity",
                      "value": "0.5",
                      "type": "text"
                    },
                    {
                      "description": {
                        "content": "A value to control randomness in generation.",
                        "type": "text/plain"
                      },
                      "key": "seed",
                      "value": "0",
                      "type": "text"
                    },
                    {
                      "description": {
                        "content": "The output format of the generated image. (This can only be one of jpeg,png,webp)",
                        "type": "text/plain"
                      },
                      "key": "output_format",
                      "value": "png",
                      "type": "text"
                    }
                  ]
                }
              },
              "status": "Bad Request",
              "code": 400,
              "header": [
                {
                  "key": "Content-Type",
                  "value": "application/json"
                }
              ],
              "body": "{\n  \"id\": \"string\",\n  \"name\": \"string\",\n  \"message\": \"string\"\n}",
              "cookie": [],
              "_postman_previewlanguage": "json"
            },
            {
              "id": "90761c2f-2a50-4ea2-aece-a28a0781d879",
              "name": "Unauthorized due to missing or invalid API key",
              "originalRequest": {
                "url": {
                  "path": [
                    "v2beta",
                    "stable-image",
                    "control",
                    "style"
                  ],
                  "host": [
                    "{{baseUrl}}"
                  ],
                  "query": [],
                  "variable": []
                },
                "header": [
                  {
                    "description": {
                      "content": "Added as a part of security scheme: bearer",
                      "type": "text/plain"
                    },
                    "key": "Authorization",
                    "value": "Bearer <token>"
                  },
                  {
                    "key": "Accept",
                    "value": "application/json"
                  }
                ],
                "method": "POST",
                "body": {
                  "mode": "formdata",
                  "formdata": [
                    {
                      "description": {
                        "content": "(Required) The style reference image whose visual style will be applied to the output.",
                        "type": "text/plain"
                      },
                      "key": "image",
                      "value": "<binary>",
                      "type": "text"
                    },
                    {
                      "description": {
                        "content": "(Required) Text describing the subject and composition of the output image.",
                        "type": "text/plain"
                      },
                      "key": "prompt",
                      "value": "<string>",
                      "type": "text"
                    },
                    {
                      "description": {
                        "content": "Text describing elements to exclude from the output image.",
                        "type": "text/plain"
                      },
                      "key": "negative_prompt",
                      "value": "<string>",
                      "type": "text"
                    },
                    {
                      "description": {
                        "content": "Controls how strongly the style of the reference image influences the output. Higher values produce outputs closer to the reference style.",
                        "type": "text/plain"
                      },
                      "key": "fidelity",
                      "value": "0.5",
                      "type": "text"
                    },
                    {
                      "description": {
                        "content": "A value to control randomness in generation.",
                        "type": "text/plain"
                      },
                      "key": "seed",
                      "value": "0",
                      "type": "text"
                    },
                    {
                      "description": {
                        "content": "The output format of the generated image. (This can only be one of jpeg,png,webp)",
                        "type": "text/plain"
                      },
                      "key": "output_format",
                      "value": "png",
                      "type": "text"
                    }
                  ]
                }
              },
              "status": "Unauthorized",
              "code": 401,
              "header": [
                {
                  "key": "Content-Type",
                  "value": "application/json"
                }
              ],
              "body": "{\n  \"id\": \"string\",\n  \"name\": \"string\",\n  \"message\": \"string\"\n}",
              "cookie": [],
              "_postman_previewlanguage": "json"
            },
            {
              "id": "0cae4397-caef-4754-a85c-1b9ea4e72d6e",
              "name": "Forbidden due to content moderation or insufficient permissions",
              "originalRequest": {
                "url": {
                  "path": [
                    "v2beta",
                    "stable-image",
                    "control",
                    "style"
                  ],
                  "host": [
                    "{{baseUrl}}"
                  ],
                  "query": [],
                  "variable": []
                },
                "header": [
                  {
                    "description": {
                      "content": "Added as a part of security scheme: bearer",
                      "type": "text/plain"
                    },
                    "key": "Authorization",
                    "value": "Bearer <token>"
                  },
                  {
                    "key": "Accept",
                    "value": "application/json"
                  }
                ],
                "method": "POST",
                "body": {
                  "mode": "formdata",
                  "formdata": [
                    {
                      "description": {
                        "content": "(Required) The style reference image whose visual style will be applied to the output.",
                        "type": "text/plain"
                      },
                      "key": "image",
                      "value": "<binary>",
                      "type": "text"
                    },
                    {
                      "description": {
                        "content": "(Required) Text describing the subject and composition of the output image.",
                        "type": "text/plain"
                      },
                      "key": "prompt",
                      "value": "<string>",
                      "type": "text"
                    },
                    {
                      "description": {
                        "content": "Text describing elements to exclude from the output image.",
                        "type": "text/plain"
                      },
                      "key": "negative_prompt",
                      "value": "<string>",
                      "type": "text"
                    },
                    {
                      "description": {
                        "content": "Controls how strongly the style of the reference image influences the output. Higher values produce outputs closer to the reference style.",
                        "type": "text/plain"
                      },
                      "key": "fidelity",
                      "value": "0.5",
                      "type": "text"
                    },
                    {
                      "description": {
                        "content": "A value to control randomness in generation.",
                        "type": "text/plain"
                      },
                      "key": "seed",
                      "value": "0",
                      "type": "text"
                    },
                    {
                      "description": {
                        "content": "The output format of the generated image. (This can only be one of jpeg,png,webp)",
                        "type": "text/plain"
                      },
                      "key": "output_format",
                      "value": "png",
                      "type": "text"
                    }
                  ]
                }
              },
              "status": "Forbidden",
              "code": 403,
              "header": [
                {
                  "key": "Content-Type",
                  "value": "application/json"
                }
              ],
              "body": "{\n  \"id\": \"string\",\n  \"name\": \"string\",\n  \"message\": \"string\"\n}",
              "cookie": [],
              "_postman_previewlanguage": "json"
            },
            {
              "id": "e8391533-a2e3-438a-9d5c-78c627df114d",
              "name": "Rate limit exceeded",
              "originalRequest": {
                "url": {
                  "path": [
                    "v2beta",
                    "stable-image",
                    "control",
                    "style"
                  ],
                  "host": [
                    "{{baseUrl}}"
                  ],
                  "query": [],
                  "variable": []
                },
                "header": [
                  {
                    "description": {
                      "content": "Added as a part of security scheme: bearer",
                      "type": "text/plain"
                    },
                    "key": "Authorization",
                    "value": "Bearer <token>"
                  },
                  {
                    "key": "Accept",
                    "value": "application/json"
                  }
                ],
                "method": "POST",
                "body": {
                  "mode": "formdata",
                  "formdata": [
                    {
                      "description": {
                        "content": "(Required) The style reference image whose visual style will be applied to the output.",
                        "type": "text/plain"
                      },
                      "key": "image",
                      "value": "<binary>",
                      "type": "text"
                    },
                    {
                      "description": {
                        "content": "(Required) Text describing the subject and composition of the output image.",
                        "type": "text/plain"
                      },
                      "key": "prompt",
                      "value": "<string>",
                      "type": "text"
                    },
                    {
                      "description": {
                        "content": "Text describing elements to exclude from the output image.",
                        "type": "text/plain"
                      },
                      "key": "negative_prompt",
                      "value": "<string>",
                      "type": "text"
                    },
                    {
                      "description": {
                        "content": "Controls how strongly the style of the reference image influences the output. Higher values produce outputs closer to the reference style.",
                        "type": "text/plain"
                      },
                      "key": "fidelity",
                      "value": "0.5",
                      "type": "text"
                    },
                    {
                      "description": {
                        "content": "A value to control randomness in generation.",
                        "type": "text/plain"
                      },
                      "key": "seed",
                      "value": "0",
                      "type": "text"
                    },
                    {
                      "description": {
                        "content": "The output format of the generated image. (This can only be one of jpeg,png,webp)",
                        "type": "text/plain"
                      },
                      "key": "output_format",
                      "value": "png",
                      "type": "text"
                    }
                  ]
                }
              },
              "status": "Too Many Requests",
              "code": 429,
              "header": [
                {
                  "key": "Content-Type",
                  "value": "application/json"
                }
              ],
              "body": "{\n  \"id\": \"string\",\n  \"name\": \"string\",\n  \"message\": \"string\"\n}",
              "cookie": [],
              "_postman_previewlanguage": "json"
            }
          ],
          "event": [],
          "protocolProfileBehavior": {
            "disableBodyPruning": true
          }
        }
      ],
      "event": []
    }
  ],
  "event": [],
  "variable": [
    {
      "type": "string",
      "value": "https://api.stability.ai",
      "key": "baseUrl"
    }
  ],
  "auth": {
    "type": "bearer",
    "bearer": [
      {
        "key": "token",
        "value": "{{bearerToken}}"
      }
    ]
  },
  "info": {
    "_postman_id": "46136b42-3332-460f-bedd-3562da5f67aa",
    "name": "Stability AI Stable Image Control API",
    "schema": "https://schema.getpostman.com/json/collection/v2.1.0/collection.json",
    "description": {
      "content": "The Stability AI Stable Image Control API provides image-to-image generation guided by structural inputs such as sketches, reference structures, and style guides. Using ControlNet-based models, developers can generate new images that follow the composition, edges, or layout of a source image while applying new styles or content based on text prompts. The API supports sketch-to-image, structure-guided generation, and style transfer workflows.\n\nContact Support:\n Name: Stability AI Support",
      "type": "text/plain"
    }
  }
}